Metadata-Version: 2.1
Name: automateboringstuff1stedition
Version: 1.0.4
Summary: This package installs the modules used in "Automate the Boring Stuff with Python", 1st Edition.
Home-page: https://github.com/asweigart/automateboringstuff1stedition
Author: Al Sweigart
Author-email: al@inventwithpython.com
License: BSD
Keywords: automate boring stuff python
Platform: UNKNOWN
Classifier: Development Status :: 5 - Production/Stable
Classifier: Environment :: Win32 (MS Windows)
Classifier: Environment :: X11 Applications
Classifier: Environment :: MacOS X
Classifier: Intended Audience :: Developers
Classifier: License :: OSI Approved :: BSD License
Classifier: Operating System :: OS Independent
Classifier: Programming Language :: Python
Classifier: Programming Language :: Python :: 3
Classifier: Programming Language :: Python :: 3.5
Classifier: Programming Language :: Python :: 3.6
Classifier: Programming Language :: Python :: 3.7
Classifier: Programming Language :: Python :: 3.8
Classifier: Programming Language :: Python :: 3.9
Classifier: Programming Language :: Python :: 3.10
